guanin/INSTALL.txt
guanin/changelog.md
guanin/cli.py
guanin/examples/d1_COV_GSE183071/GSM5550565_B0248-Blood.RCC
guanin/examples/d1_COV_GSE183071/GSM5550568_B0250-Blood.RCC
guanin/examples/d1_COV_GSE183071/GSM5550571_B0314-Blood.RCC
guanin/examples/d1_COV_GSE183071/GSM5550574_B0315-Blood.RCC
guanin/examples/d1_COV_GSE183071/GSM5550577_B0317-Blood.RCC
guanin/examples/d1_COV_GSE183071/GSM5550580_B0318-Blood.RCC
guanin/examples/d1_COV_GSE183071/GSM5550583_B0319-Blood.RCC
guanin/examples/d1_COV_GSE183071/GSM5550585_B0328-Blood.RCC
guanin/examples/d1_COV_GSE183071/GSM5550586_B0329-Blood.RCC
guanin/examples/d1_COV_GSE183071/GSM5550588_B0331-Blood.RCC
guanin/examples/d1_COV_GSE183071/GSM5550592_B0334-Blood.RCC
guanin/examples/d1_COV_GSE183071/GSM5550594_B0335-Blood.RCC
guanin/examples/d1_COV_GSE183071/GSM5550597_B0338-Blood.RCC
guanin/examples/d1_COV_GSE183071/GSM5550598_B0342-Blood.RCC
guanin/examples/d1_COV_GSE183071/GSM5550600_B0343-Blood.RCC
guanin/examples/d1_COV_GSE183071/GSM5550607_B0354-Blood.RCC
guanin/examples/d1_COV_GSE183071/GSM5550608_B0361-Blood.RCC
guanin/examples/d1_COV_GSE183071/GSM5550611_B0368-Blood.RCC
guanin/examples/d1_COV_GSE183071/GSM5550614_B0369-Blood.RCC
guanin/examples/d1_COV_GSE183071/GSM5550617_B0372-Blood.RCC
guanin/examples/d1_COV_GSE183071/GSM5550620_B0374-Blood.RCC
guanin/examples/d1_COV_GSE183071/GSM5550623_B0375-Blood.RCC
guanin/examples/d1_COV_GSE183071/GSM5550626_B0380-Blood.RCC
guanin/examples/d1_COV_GSE183071/GSM5550629_B0381-Blood.RCC
guanin/examples/d1_COV_GSE183071/GSM5550632_B0393-Blood.RCC
guanin/examples/d1_COV_GSE183071/GSM5550635_B0396-Blood.RCC
guanin/examples/d1_COV_GSE183071/GSM5550638_B0399-Blood.RCC
guanin/examples/d1_COV_GSE183071/GSM5550643_B0406-Blood.RCC
guanin/examples/d1_COV_GSE183071/GSM5550646_B0408-Blood.RCC
guanin/examples/d1_COV_GSE183071/GSM5550649_B0415-Blood.RCC
guanin/examples/d1_COV_GSE183071/GSM5550652_B0428-Blood.RCC
guanin/examples/d1_COV_GSE183071/GSM5550655_B0440-Blood.RCC
guanin-1.2.14.dist-info/LICENSE
guanin-1.2.14.dist-info/METADATA
guanin-1.2.14.dist-info/WHEEL
guanin-1.2.14.dist-info/entry_points.txt
guanin-1.2.14.dist-info/RECORD
