Metadata-Version: 2.1
Name: guanin
Version: 1.2.14
Summary: 
Author: Julián Montoto-Louzao
Requires-Python: >=3.9,<4.0
Classifier: Programming Language :: Python :: 3
Classifier: Programming Language :: Python :: 3.9
Classifier: Programming Language :: Python :: 3.10
Classifier: Programming Language :: Python :: 3.11
Requires-Dist: PyQt6 (>=6.4,<7.0)
Requires-Dist: PyQt6-Qt6 (>=6.4,<7.0)
Requires-Dist: PyQt6-sip (>=13.4,<14.0)
Requires-Dist: ergene (>=1.2,<2.0)
Requires-Dist: fpdf (>=1.7,<2.0)
Requires-Dist: jinja2 (>=3.0,<4.0)
Requires-Dist: matplotlib (>=3.7,<4.0)
Requires-Dist: mlxtend (>=0.21,<0.22)
Requires-Dist: numpy (>=1.23,<2.0)
Requires-Dist: pandas (==1.5.3)
Requires-Dist: pip (>=24.0.0,<25.0.0)
Requires-Dist: pydeseq2 (==0.4.3)
Requires-Dist: scikit-learn (>=1.0,<2.0)
Requires-Dist: scipy (>=1.9,<2.0)
Requires-Dist: seaborn (>=0.12,<0.13)
Requires-Dist: setuptools (>=69.1.0,<70.0.0)
